django_model_prediction_service/__init__.py
django_model_prediction_service/admin.py
django_model_prediction_service/app_globals.py
django_model_prediction_service/apps.py
django_model_prediction_service/models.py
django_model_prediction_service/startup.py
django_model_prediction_service/tests.py
django_model_prediction_service/urls.py
django_model_prediction_service/views.py
django_model_prediction_service/common/__init__.py
django_model_prediction_service/common/logger.py
django_model_prediction_service/config/__init__.py
django_model_prediction_service/config/config_manager.py
django_model_prediction_service/metrics/__init__.py
django_model_prediction_service/metrics/metrics.py
django_model_prediction_service/schedule_task/__init__.py
django_model_prediction_service/schedule_task/schedule_task_manager.py
django_model_prediction_service/services/__init__.py
django_model_prediction_service/services/model_loader/__init__.py
django_model_prediction_service/services/model_loader/exceptions/ModelSourceNotConfiguredError.py
django_model_prediction_service/services/model_loader/exceptions/__init__.py
django_model_prediction_service/services/model_loader/handler/__init__.py
django_model_prediction_service/services/model_loader/handler/prediction_model_handler.py
django_model_prediction_service/services/model_loader/loader/__init__.py
django_model_prediction_service/services/model_loader/loader/model_builder_service.py
django_model_prediction_service/services/model_loader/loader/model_loader.py
django_model_prediction_service/services/model_loader/stats/__init__.py
django_model_prediction_service/services/model_loader/stats/stats_collector.py
django_model_prediction_service/services/monitoring/__init__.py
django_model_prediction_service/services/monitoring/monitoring.py
tests/__init__.py
tests/dummy_objects.py
tests/test_api.py
tests/test_model_loader.py
tests/test_prediction_service.py
tests/test_schedule_task_manager.py
tests/test_utils.py
django_model_prediction_service-1.0.27.0.dist-info/LICENSE
django_model_prediction_service-1.0.27.0.dist-info/METADATA
django_model_prediction_service-1.0.27.0.dist-info/WHEEL
django_model_prediction_service-1.0.27.0.dist-info/top_level.txt
django_model_prediction_service-1.0.27.0.dist-info/RECORD
