Metadata-Version: 2.1
Name: django-model-prediction-service
Version: 1.0.27.0
Summary: Machine learning model prediction app
Home-page: UNKNOWN
Author: lior.yehonatan
Author-email: lior.yehonatan@inel.com
License: BSD License
Platform: UNKNOWN
Requires-Python: >=3.6
Requires-Dist: swiss-logger (==1.0.3.0)
Requires-Dist: swiss-common-utils (==1.0.27.0)
Requires-Dist: prediction-model-wrapper (==1.0.13.0)
Requires-Dist: APScheduler (==3.6.0)
Requires-Dist: prometheus-client (==0.6.0)
